aiosplunkbase/__init__.py
aiosplunkbase/client.py
aiosplunkbase/exceptions.py
aiosplunkbase-0.1.3.dist-info/METADATA
aiosplunkbase-0.1.3.dist-info/WHEEL
aiosplunkbase-0.1.3.dist-info/licenses/LICENSE
aiosplunkbase-0.1.3.dist-info/RECORD
