Metadata-Version: 2.4
Name: aiosplunkbase
Version: 0.1.3
Summary: Async Python client for Splunkbase
Author: Cameron Schmidt
License: MIT
License-File: LICENSE
Requires-Python: >=3.9
Requires-Dist: httpx>=0.28.1
Requires-Dist: packaging>=24.2
